{
  "id": "battle-gen9ou-2534382011",
  "p1": "Jamez",
  "p2": "sminey",
  "minElo": 1741,
  "startTime": 1770414723324,
  "turns": [
    {
      "turn": 1,
      "events": [
        "|switch|p1a: Pecharunt|Pecharunt|100/100",
        "|switch|p2a: Zapdos|Zapdos|100/100"
      ]
    },
    {
      "turn": 2,
      "events": [
        "|switch|p2a: Slowking|Slowking-Galar, M|100/100",
        "|move|p1a: Pecharunt|Malignant Chain|p2a: Slowking"
      ]
    },
    {
      "turn": 3,
      "events": [
        "|switch|p2a: Clefable|Clefable, M|100/100",
        "|move|p1a: Pecharunt|Nasty Plot|p1a: Pecharunt"
      ]
    },
    {
      "turn": 4,
      "events": [
        "|switch|p2a: Slowking|Slowking-Galar, M|100/100",
        "|move|p1a: Pecharunt|Malignant Chain|p2a: Slowking"
      ]
    },
    {
      "turn": 5,
      "events": [
        "|move|p1a: Pecharunt|Shadow Ball|p2a: Slowking",
        "|move|p2a: Slowking|Psyshock|p1a: Pecharunt"
      ]
    },
    {
      "turn": 6,
      "events": [
        "|switch|p2a: Weavile|Weavile, M|100/100",
        "|move|p1a: Pecharunt|Shadow Ball|p2a: Weavile"
      ]
    },
    {
      "turn": 7,
      "events": [
        "|switch|p1a: Ting-Lu|Ting-Lu|100/100",
        "|move|p2a: Weavile|Knock Off|p1a: Ting-Lu"
      ]
    },
    {
      "turn": 8,
      "events": [
        "|switch|p2a: Clefable|Clefable, M|100/100",
        "|move|p1a: Ting-Lu|Stealth Rock|p2a: Clefable"
      ]
    },
    {
      "turn": 9,
      "events": [
        "|move|p2a: Clefable|Moonblast|p1a: Ting-Lu",
        "|move|p1a: Ting-Lu|Ruination|p2a: Clefable"
      ]
    },
    {
      "turn": 10,
      "events": [
        "|move|p2a: Clefable|Moonblast|p1a: Ting-Lu",
        "|move|p1a: Ting-Lu|Spikes|p2a: Clefable"
      ]
    },
    {
      "turn": 11,
      "events": [
        "|switch|p1a: Gholdengo|Gholdengo|100/100",
        "|move|p2a: Clefable|Calm Mind|p2a: Clefable"
      ]
    },
    {
      "turn": 12,
      "events": [
        "|switch|p2a: Zapdos|Zapdos|100/100",
        "|move|p1a: Gholdengo|Make It Rain|p2a: Zapdos"
      ]
    },
    {
      "turn": 13,
      "events": [
        "|switch|p1a: Darkrai|Darkrai|100/100",
        "|move|p2a: Zapdos|Hurricane|p1a: Darkrai|[miss]"
      ]
    },
    {
      "turn": 14,
      "events": [
        "|move|p1a: Darkrai|Ice Beam|p2a: Zapdos",
        "|switch|p2a: Cinderace|Cinderace, M|100/100"
      ]
    },
    {
      "turn": 15,
      "events": [
        "|move|p1a: Darkrai|Knock Off|p2a: Cinderace",
        "|move|p2a: Cinderace|Pyro Ball|p1a: Darkrai"
      ]
    },
    {
      "turn": 16,
      "events": [
        "|move|p2a: Cinderace|Sucker Punch|p1a: Darkrai",
        "|switch|p1a: Gholdengo|Gholdengo, tera:Steel|100/100"
      ]
    },
    {
      "turn": 17,
      "events": [
        "|move|p1a: Gholdengo|Make It Rain|p2a: Cinderace",
        "|switch|p2a: Slowking|Slowking-Galar, M|83/100"
      ]
    },
    {
      "turn": 18,
      "events": [
        "|switch|p1a: Ting-Lu|Ting-Lu|35/100",
        "|switch|p2a: Weavile|Weavile, M|64/100"
      ]
    },
    {
      "turn": 19,
      "events": [
        "|move|p2a: Weavile|Triple Axel|p1a: Ting-Lu",
        "|switch|p1a: Gholdengo|Gholdengo, tera:Steel|100/100"
      ]
    },
    {
      "turn": 20,
      "events": [
        "|switch|p2a: Slowking|Slowking-Galar, M|92/100",
        "|move|p1a: Gholdengo|Make It Rain|p2a: Slowking"
      ]
    },
    {
      "turn": 21,
      "events": [
        "|switch|p2a: Latios|Latios, M|100/100",
        "|move|p1a: Gholdengo|Make It Rain|p2a: Latios"
      ]
    },
    {
      "turn": 22,
      "events": [
        "|move|p2a: Latios|Flip Turn|p1a: Gholdengo",
        "|switch|p2a: Slowking|Slowking-Galar, M|63/100|[from] Flip Turn",
        "|move|p1a: Gholdengo|Make It Rain|p2a: Slowking"
      ]
    },
    {
      "turn": 23,
      "events": [
        "|move|p1a: Gholdengo|Make It Rain|p2a: Slowking",
        "|move|p2a: Slowking|Flamethrower|p1a: Gholdengo"
      ]
    },
    {
      "turn": 24,
      "events": [
        "|switch|p1a: Pecharunt|Pecharunt|63/100",
        "|move|p2a: Slowking|Flamethrower|p1a: Pecharunt"
      ]
    },
    {
      "turn": 25,
      "events": [
        "|move|p1a: Pecharunt|Malignant Chain|p2a: Slowking",
        "|switch|p2a: Weavile|Weavile, M|64/100"
      ]
    },
    {
      "turn": 26,
      "events": [
        "|move|p2a: Weavile|Knock Off|p1a: Pecharunt",
        "|switch|p1a: Clefable|Clefable, F|100/100"
      ]
    },
    {
      "turn": 27,
      "events": [
        "|move|p2a: Weavile|Swords Dance|p2a: Weavile",
        "|move|p1a: Clefable|Moonblast|p2a: Weavile",
        "|switch|p2a: Clefable|Clefable, M|50/100"
      ]
    },
    {
      "turn": 28,
      "events": [
        "|move|p1a: Clefable|Moonblast|p2a: Clefable",
        "|move|p2a: Clefable|Calm Mind|p2a: Clefable"
      ]
    },
    {
      "turn": 29,
      "events": [
        "|move|p1a: Clefable|Moonblast|p2a: Clefable",
        "|switch|p2a: Latios|Latios, M|30/100"
      ]
    },
    {
      "turn": 30,
      "events": [
        "|move|p2a: Latios|Luster Purge|p1a: Clefable",
        "|move|p1a: Clefable|Moonblast|p2a: Latios"
      ]
    }
  ],
  "winner": "Jamez",
  "endTime": 1770415264449,
  "p1Team": [
    "Pecharunt",
    "Ting-Lu",
    "Gholdengo",
    "Darkrai",
    "Clefable"
  ],
  "p2Team": [
    "Zapdos",
    "Slowking-Galar",
    "Clefable",
    "Weavile",
    "Cinderace",
    "Latios"
  ],
  "p1Classification": {
    "archetype": "offensive",
    "confidence": 0.4,
    "fatCount": 1,
    "offenseCount": 2,
    "team": [
      "pecharunt",
      "tinglu",
      "gholdengo",
      "darkrai",
      "clefable"
    ],
    "isFat": false,
    "isOffensive": true
  },
  "p2Classification": {
    "archetype": "fat",
    "confidence": 0.5,
    "fatCount": 3,
    "offenseCount": 0,
    "team": [
      "zapdos",
      "slowkinggalar",
      "clefable",
      "weavile",
      "cinderace",
      "latios"
    ],
    "isFat": true,
    "isOffensive": false
  },
  "relevantToBot": true,
  "learningValue": "LOSS_WITH_OUR_ARCHETYPE"
}