{
  "timestamp": "20260201_073243",
  "replay_url": "https://replay.pokemonshowdown.com/gen9ou-2530608074",
  "replay_id": "gen9ou-2530608074",
  "mistakes_found": 3,
  "mistakes": [
    {
      "category": "pokemon_fainted",
      "turn": 25,
      "description": "Ninetales fainted - possible switching error",
      "severity": "major",
      "suggested_fix": "Improve switching logic to preserve Pokemon"
    },
    {
      "category": "no_hazards_set",
      "turn": 33,
      "description": "Never set up hazards (critical for chip damage)",
      "severity": "major",
      "suggested_fix": "Increase hazard priority in scoring"
    },
    {
      "category": "hazards_not_removed",
      "turn": 33,
      "description": "Opponent set hazards, bot didn't remove them",
      "severity": "minor",
      "suggested_fix": "Add defog/rapid spin priority when hazards are up"
    }
  ]
}