{
  "timestamp": "20260131_150556",
  "replay_url": "https://replay.pokemonshowdown.com/gen9ou-2530217759",
  "replay_id": "gen9ou-2530217759",
  "mistakes_found": 8,
  "mistakes": [
    {
      "category": "pokemon_fainted",
      "turn": 4,
      "description": "Gliscor fainted - possible switching error",
      "severity": "major",
      "suggested_fix": "Improve switching logic to preserve Pokemon"
    },
    {
      "category": "pokemon_fainted",
      "turn": 6,
      "description": "Gholdengo fainted - possible switching error",
      "severity": "major",
      "suggested_fix": "Improve switching logic to preserve Pokemon"
    },
    {
      "category": "pokemon_fainted",
      "turn": 19,
      "description": "Zamazenta fainted - possible switching error",
      "severity": "major",
      "suggested_fix": "Improve switching logic to preserve Pokemon"
    },
    {
      "category": "pokemon_fainted",
      "turn": 37,
      "description": "Skarmory fainted - possible switching error",
      "severity": "major",
      "suggested_fix": "Improve switching logic to preserve Pokemon"
    },
    {
      "category": "pokemon_fainted",
      "turn": 39,
      "description": "Pecharunt fainted - possible switching error",
      "severity": "major",
      "suggested_fix": "Improve switching logic to preserve Pokemon"
    },
    {
      "category": "pokemon_fainted",
      "turn": 44,
      "description": "Blissey fainted - possible switching error",
      "severity": "major",
      "suggested_fix": "Improve switching logic to preserve Pokemon"
    },
    {
      "category": "hazards_not_removed",
      "turn": 44,
      "description": "Opponent set hazards, bot didn't remove them",
      "severity": "minor",
      "suggested_fix": "Add defog/rapid spin priority when hazards are up"
    },
    {
      "category": "early_setup",
      "turn": 4,
      "description": "Attempted swordsdance on turn 4 (too early?)",
      "severity": "minor",
      "suggested_fix": "Delay setup until opponent is weakened"
    }
  ]
}