{
  "turn": 21,
  "bot_choice": "Pecharunt fainted",
  "why_critical": "\u274c Pecharunt fainted \u2014 should we have switched out earlier or chosen differently?",
  "bot_team": "Gliscor fainted | Gholdengo fainted | Zamazenta-* 100% | Blissey 100% | Skarmory 100% | Pecharunt 27% par | Zamazenta 56%",
  "opp_team": "Ninetales 100% | Walking Wake 63% tox | Corviknight 71% | Chansey 88% | Great Tusk 71% -1 def, -1 spd | Enamorus 100%",
  "field": [],
  "replay_url": "https://replay.pokemonshowdown.com/gen9ou-2530335714",
  "alternatives": [
    [
      "Switch out earlier",
      "Preserve this Pokemon for later"
    ],
    [
      "Different move",
      "Better damage/utility before going down"
    ]
  ],
  "feedback": null
}